{
  "$schema": "https://mintlify.com/docs.json",
  "theme": "mint",
  "name": "SketricGen Docs",
  "colors": {
    "primary": "#7D4AEA",
    "light": "#7D4AEA",
    "dark": "#7D4AEA"
  },
  "favicon": "favicon.ico",
  "navigation": {
    "tabs": [
      {
        "tab": "Documentation",
        "groups": [
          {
            "group": "Getting Started",
            "pages": [
              "getting-started/overview",
              "getting-started/core-concepts",
              "getting-started/quickstart"
            ]
          },
          {
            "group": "User Guides",
            "pages": [
              "user-guides/agentspace-canvas",
              "user-guides/agents",
              "user-guides/tools",
              "user-guides/orchestration-and-handoffs",
              "user-guides/structured-inputs-and-outputs",
              "user-guides/traces-and-optimizations",
              "user-guides/conversations-and-insights",
              "user-guides/advanced-agent-settings",
              "user-guides/best-practices"
            ]
          },
          {
            "group": "Deploy",
            "pages": [
              "deploy/whatsapp",
              "deploy/squarespace",
              "deploy/wix",
              "deploy/slack",
              "deploy/telegram",
              "deploy/instagram",
              "deploy/shopify",
              "deploy/wordpress",
              "deploy/zapier",
              "deploy/framer",
              "deploy/custom-website"
            ]
          },
          {
            "group": "Dev Guide",
            "pages": [
              "dev-guide/public-api-usage",
              "dev-guide/python-sdk",
              "dev-guide/contacts"
            ]
          },
          {
            "group": "Product Updates",
            "pages": [
              {
                "group": "2026 Updates",
                "pages": [
                  "changelog/2026-01-21-onboarding-infinite-scroll-tool-management",
                  "changelog/2026-01-13-app-landing-auth-flow-workflow-scheduling-integrations"
                ]
              },
              {
                "group": "2025 Updates",
                "expanded": false,
                "pages": [
                  "changelog/2025-12-29-node-inspector-editing-image-gen-integrations-performance",
                  "changelog/2025-12-15-billing-fixes-integrations-onboarding",
                  "changelog/2025-12-13-chat-widget-file-upload-guided-tour-advanced-agent-settings",
                  "changelog/2025-11-26-conversations-contacts-attachments-instagram-zapier",
                  "changelog/2025-11-17-telegram-google-signin-mobile-integrations",
                  "changelog/2025-11-07-affiliate-referrals-widget-import-ui",
                  "changelog/2025-11-03-iframe-fullscreen-embed-forced-handoff-ga-tracking",
                  "changelog/2025-10-24-message-tracing-templates-ui-integrations"
                ]
              },
              {
                "group": "Major Releases",
                "expanded": false,
                "pages": [
                  "changelog/v2.0.0",
                  "changelog/v1.0.0"
                ]
              }
            ]
          }
        ]
      }
    ],
    "global": {
      "anchors": [
        {
          "anchor": "Overview",
          "icon": "book-open",
          "href": "https://docs.sketricgen.ai"
        }
      ]
    }
  },
  "logo": {
    "light": "/logo/light.png",
    "dark": "/logo/dark.png"
  },
  "navbar": {
    "links": [
      {
        "label": "Support",
        "href": "https://www.sketricgen.ai"
      }
    ],
    "primary": {
      "type": "button",
      "label": "Homepage",
      "href": "https://www.sketricgen.ai"
    }
  },
  "footer": {
    "socials": {
      "linkedin": "https://www.linkedin.com/company/sketricgen",
      "facebook": "https://www.facebook.com/profile.php?id=61574534166470",
      "instagram": "https://www.instagram.com/sketricgen/"
    }
  }
}